design.sv
// Code your design here
module i2c #(
    address_width = 8 , data = 8
) (
    inout wire [7:0] sda,
    output reg scl,
    input logic clk,
    input logic rst_n,
    input logic [address_width-1:0] address
);
    logic data_valid , adress_valid , stop;
    logic [6:0] counter;
    logic read, write;
    logic [4:0] bit_counter;
    logic adress_state;
    logic drive_low;
    logic ack_received;
    logic [data-1:0] data_reg;
    logic [address_width-1:0] address_reg;
    logic [1:0] state;
    logic sda_in;
    logic stop_generated;
    logic start_detected;

    wire start;
    wire ack;

    assign sda_in = sda[0];

    always_ff @( posedge clk or negedge rst_n ) begin : scl_tick
        if(!rst_n) begin
            scl <= 0;
            counter <= 0;
        end
        else if(counter == 9) begin
            counter <= 0;
            scl <= ~scl;
        end else begin
            counter <= counter + 1'b1;
        end
    end

    // Continuous assignments for combinational signals
    assign start = (scl && (bit_counter <= 8) && !sda_in) ? 1'b1 : 1'b0;
    assign ack = (bit_counter == 9 && !sda_in && scl) ? 1'b1 : 1'b0;

    assign sda = (drive_low) ? 8'b0 : 8'bz;

    always @(posedge clk or negedge rst_n) begin
        if (!rst_n) begin
            bit_counter <= 0;
            drive_low <= 0;
            read <= 0;
            write <= 0;
            adress_valid <= 0;
            data_valid <= 0;
            stop <= 0;
            adress_state <= 0;
            ack_received <= 0;
            address_reg <= 0;
            data_reg <= 0;
            state <= 0;
            stop_generated <= 0;
            start_detected <= 0;
        end else if (start && (bit_counter <= 8)) begin
            bit_counter <= bit_counter + 1'b1;
            start_detected <= 1;
            if (address_reg[address_width-1]) begin
                drive_low <= 1'b0;
            end else begin
                drive_low <= 1'b1;
            end
            if (bit_counter == 8) begin
                if(sda_in == 1'b1)
                    read <= 1'b1;
                else
                    write <= 1'b1;
            end
        end else if (ack) begin
            ack_received <= 1'b1;
            bit_counter <= 0;
            drive_low <= 0;
            if(adress_state == 0) begin
                adress_state <= 1;
                adress_valid <= 1;
            end else begin
                data_valid <= 1;
            end
        end else if(adress_state && write && bit_counter < data) begin
            if(scl == 0) begin
                bit_counter <= bit_counter + 1;
                if(address[bit_counter])
                    drive_low <= 1'b1;
                else
                    drive_low <= 1'b0;
            end
        end else if(adress_state && read && bit_counter < data) begin
            if(scl == 0) begin
                bit_counter <= bit_counter + 1;
                drive_low <= 0;
            end
        end else if(bit_counter == data && scl == 0) begin
            bit_counter <= 0;
            drive_low <= 0;
            if(write) begin
                write <= 0;
                stop_generated <= 1;
            end else if(read) begin
                read <= 0;
                stop_generated <= 1;
            end
        end else if(stop_generated && scl == 1) begin
            drive_low <= 0;
            stop <= 1;
            stop_generated <= 0;
            adress_state <= 0;
            start_detected <= 0;
        end
    end
endmodule

testbench.sv
`timescale 1ns / 1ps

module i2c_tb;
    parameter address_width = 8;
    parameter data = 8;
    
    wire [7:0] sda;
    wire scl;
    reg clk;
    reg rst_n;
    reg [address_width-1:0] address;
    
    i2c #(
        .address_width(address_width),
        .data(data)
    ) uut (
        .sda(sda),
        .scl(scl),
        .clk(clk),
        .rst_n(rst_n),
        .address(address)
    );
    
    reg [7:0] sda_drive;
    reg sda_oe;
    
    assign sda = sda_oe ? sda_drive : 8'bz;
    
    initial begin
        clk = 0;
        forever #10 clk = ~clk;
    end
    
    initial begin
        $monitor("Time=%0t, scl=%b, sda=%b, address=%h, read=%b, write=%b, bit_counter=%d, adress_state=%b, stop=%b, start=%b", 
                 $time, scl, sda, uut.address_reg, uut.read, uut.write, uut.bit_counter, uut.adress_state, uut.stop, uut.start);
    end
    
    initial begin
        rst_n = 0;
        address = 8'hA0;
        sda_oe = 0;
        sda_drive = 8'bz;
        
        #100;
        rst_n = 1;
        #50;
        
        $display("\n=== Test 1: START Condition ===");
        simulate_start();
        #200;
        
        $display("\n=== Test 2: Address Write ===");
        send_byte(8'hA0, 1);
        #500;
        
        $display("\n=== Test 3: Data Write ===");
        send_byte(8'h55, 1);
        #500;
        
        $display("\n=== Test 4: STOP Condition ===");
        simulate_stop();
        #500;
        
        $display("\n=== Test 5: Address Read ===");
        simulate_start();
        send_byte(8'hA1, 1);
        #500;
        
        $display("\n=== Test 6: Data Read ===");
        receive_byte(8'hAA);
        #500;
        
        $display("\n=== Test 7: Final STOP ===");
        simulate_stop();
        #500;
        
        $display("\n=== Test 8: Multiple Transactions ===");
        for(int i = 0; i < 3; i++) begin
            simulate_start();
            send_byte(8'hA0, 1);
            send_byte(8'h30 + i, 1);
            simulate_stop();
            #300;
        end
        
        $display("\n=== Test Complete ===");
        #500;
        $finish;
    end
    
    task simulate_start();
        begin
            sda_oe = 1;
            sda_drive = 8'b0;
            #40;
            #100;
            sda_oe = 0;
        end
    endtask
    
    task simulate_stop();
        begin
            sda_oe = 1;
            sda_drive = 8'b0;
            #20;
            sda_oe = 0;
            #40;
        end
    endtask
    
    task send_byte(input [7:0] byte_data, input expect_ack);
        begin
            sda_oe = 1;
            for(int i = 7; i >= 0; i--) begin
                wait(scl == 0);
                #5;
                if(byte_data[i])
                    sda_drive = 8'bz;
                else
                    sda_drive = 8'b0;
                wait(scl == 1);
                #40;
            end
            wait(scl == 0);
            #5;
            if(expect_ack)
                sda_drive = 8'b0;
            else
                sda_drive = 8'bz;
            wait(scl == 1);
            #40;
            sda_oe = 0;
            #20;
        end
    endtask
    
    task receive_byte(input [7:0] slave_response);
        begin
            sda_oe = 1;
            for(int i = 7; i >= 0; i--) begin
                wait(scl == 0);
                #5;
                if(slave_response[i])
                    sda_drive = 8'bz;
                else
                    sda_drive = 8'b0;
                wait(scl == 1);
                #40;
            end
            wait(scl == 0);
            #5;
            sda_drive = 8'b0;
            wait(scl == 1);
            #40;
            sda_oe = 0;
            #20;
        end
    endtask
    
    initial begin
        $dumpfile("i2c_tb.vcd");
        $dumpvars(0, i2c_tb);
    end
    
endmodule

i2c_tb.vcd
$date
    Jun 15, 2026  13:28:58
$end
$version
    TOOL:	xmsim	25.03-s001
$end
$timescale
    1 ps
$end

$scope module i2c_tb $end
$var parameter 32 !    address_width $end
$var parameter 32 "    data $end
$var wire      8 #    sda [7:0] $end
$var wire      1 $    scl  $end
$var reg       1 %    clk $end
$var reg       1 &    rst_n $end
$var reg       8 '    address [7:0] $end
$var reg       8 (    sda_drive [7:0] $end
$var reg       1 )    sda_oe $end

$scope module uut $end
$var parameter 32 *    address_width $end
$var parameter 32 +    data $end
$var wire      8 #    sda [7:0] $end
$var reg       1 ,    scl $end
$var wire      1 -    clk  $end
$var wire      1 .    rst_n  $end
$var wire      8 /    address [7:0] $end
$var reg       1 0    data_valid $end
$var reg       1 1    adress_valid $end
$var reg       1 2    stop $end
$var reg       7 3    counter [6:0] $end
$var reg       1 4    read $end
$var reg       1 5    write $end
$var reg       5 6    bit_counter [4:0] $end
$var reg       1 7    adress_state $end
$var reg       1 8    drive_low $end
$var reg       1 9    ack_received $end
$var reg       8 :    data_reg [7:0] $end
$var reg       8 ;    address_reg [7:0] $end
$var reg       2 <    state [1:0] $end
$var reg       1 =    sda_in $end
$var reg       1 >    stop_generated $end
$var reg       1 ?    start_detected $end
$var wire      1 @    start  $end
$var wire      1 A    ack  $end
$upscope $end


$scope task send_byte $end
$var reg       8 B    byte_data [7:0] $end
$var reg       1 C    expect_ack $end
$upscope $end


$scope task receive_byte $end
$var reg       8 D    slave_response [7:0] $end
$upscope $end

$upscope $end

$enddefinitions $end
$dumpvars
b1000 +
b1000 *
b1000 "
b1000 !
bz #
0$
0%
0&
b10100000 '
bz (
0)
0,
0-
0.
b10100000 /
00
01
02
b0 3
04
05
b0 6
07
08
09
b0 :
b0 ;
b0 <
z=
0>
0?
0@
0A
bx B
xC
bx D
$end
#10000
1%
1-
#20000
0%
0-
#30000
1%
1-
#40000
0%
0-
#50000
1%
1-
#60000
0%
0-
#70000
1%
1-
#80000
0%
0-
#90000
1%
1-
#100000
1&
0%
0-
1.
#110000
1%
1-
b1 3
#120000
0%
0-
#130000
1%
1-
b10 3
#140000
0%
0-
#150000
1)
b0 (
1%
1-
b0 #
0=
b11 3
#160000
0%
0-
#170000
1%
1-
b100 3
#180000
0%
0-
#190000
1%
1-
b101 3
#200000
0%
0-
#210000
1%
1-
b110 3
#220000
0%
0-
#230000
1%
1-
b111 3
#240000
0%
0-
#250000
1%
1-
b1000 3
#260000
0%
0-
#270000
1%
1-
b1001 3
#280000
0%
0-
#290000
0)
1%
1-
bz #
z=
b0 3
1,
x@
1$
#300000
0%
0-
#310000
1%
1-
b1 3
#320000
0%
0-
#330000
1%
1-
b10 3
#340000
0%
0-
#350000
1%
1-
b11 3
#360000
0%
0-
#370000
1%
1-
b100 3
#380000
0%
0-
#390000
1%
1-
b101 3
#400000
0%
0-
#410000
1%
1-
b110 3
#420000
0%
0-
#430000
1%
1-
b111 3
#440000
0%
0-
#450000
1%
1-
b1000 3
#460000
0%
0-
#470000
1%
1-
b1001 3
#480000
0%
0-
#490000
b10100000 B
1C
1)
1%
1-
b0 #
0=
1@
b0 3
0,
0@
0$
#495000
bz (
bz #
z=
#500000
0%
0-
#510000
1%
1-
b1 3
#520000
0%
0-
#530000
1%
1-
b10 3
#540000
0%
0-
#550000
1%
1-
b11 3
#560000
0%
0-
#570000
1%
1-
b100 3
#580000
0%
0-
#590000
1%
1-
b101 3
#600000
0%
0-
#610000
1%
1-
b110 3
#620000
0%
0-
#630000
1%
1-
b111 3
#640000
0%
0-
#650000
1%
1-
b1000 3
#660000
0%
0-
#670000
1%
1-
b1001 3
#680000
0%
0-
#690000
1%
1-
b0 3
1,
x@
1$
#700000
0%
0-
#710000
1%
1-
b1 3
#720000
0%
0-
#730000
1%
1-
b10 3
#740000
0%
0-
#750000
1%
1-
b11 3
#760000
0%
0-
#770000
1%
1-
b100 3
#780000
0%
0-
#790000
1%
1-
b101 3
#800000
0%
0-
#810000
1%
1-
b110 3
#820000
0%
0-
#830000
1%
1-
b111 3
#840000
0%
0-
#850000
1%
1-
b1000 3
#860000
0%
0-
#870000
1%
1-
b1001 3
#880000
0%
0-
#890000
1%
1-
b0 3
0,
0@
0$
#895000
b0 (
b0 #
0=
#900000
0%
0-
#910000
1%
1-
b1 3
#920000
0%
0-
#930000
1%
1-
b10 3
#940000
0%
0-
#950000
1%
1-
b11 3
#960000
0%
0-
#970000
1%
1-
b100 3
#980000
0%
0-
#990000
1%
1-
b101 3
#1000000
0%
0-
#1010000
1%
1-
b110 3
#1020000
0%
0-
#1030000
1%
1-
b111 3
#1040000
0%
0-
#1050000
1%
1-
b1000 3
#1060000
0%
0-
#1070000
1%
1-
b1001 3
#1080000
0%
0-
#1090000
1%
1-
b0 3
1,
1@
1$
#1100000
0%
0-
#1110000
1%
1-
b1 6
1?
18
b1 3
#1120000
0%
0-
#1130000
1%
1-
b10 6
b10 3
#1140000
0%
0-
#1150000
1%
1-
b11 6
b11 3
#1160000
0%
0-
#1170000
1%
1-
b100 6
b100 3
#1180000
0%
0-
#1190000
1%
1-
b101 6
b101 3
#1200000
0%
0-
#1210000
1%
1-
b110 6
b110 3
#1220000
0%
0-
#1230000
1%
1-
b111 6
b111 3
#1240000
0%
0-
#1250000
1%
1-
b1000 6
b1000 3
#1260000
0%
0-
#1270000
1%
1-
b1001 6
15
b1001 3
1A
0@
#1280000
0%
0-
#1290000
1%
1-
19
b0 6
08
17
11
b0 3
0,
0A
0$
#1295000
bz (
bz #
z=
#1300000
0%
0-
#1310000
1%
1-
b1 6
b1 3
#1320000
0%
0-
#1330000
1%
1-
b10 6
b10 3
#1340000
0%
0-
#1350000
1%
1-
b11 6
b11 3
#1360000
0%
0-
#1370000
1%
1-
b100 6
b100 3
#1380000
0%
0-
#1390000
1%
1-
b101 6
b101 3
#1400000
0%
0-
#1410000
1%
1-
b110 6
18
b110 3
b0 #
0=
#1420000
0%
0-
#1430000
1%
1-
b111 6
08
b111 3
bz #
z=
#1440000
0%
0-
#1450000
1%
1-
b1000 6
18
b1000 3
b0 #
0=
#1460000
0%
0-
#1470000
1%
1-
b0 6
08
05
1>
b1001 3
bz #
z=
#1480000
0%
0-
#1490000
1%
1-
b0 3
1,
x@
1$
#1500000
0%
0-
#1510000
1%
1-
12
0>
07
0?
b1 3
#1520000
0%
0-
#1530000
1%
1-
b10 3
#1540000
0%
0-
#1550000
1%
1-
b11 3
#1560000
0%
0-
#1570000
1%
1-
b100 3
#1580000
0%
0-
#1590000
1%
1-
b101 3
#1600000
0%
0-
#1610000
1%
1-
b110 3
#1620000
0%
0-
#1630000
1%
1-
b111 3
#1640000
0%
0-
#1650000
1%
1-
b1000 3
#1660000
0%
0-
#1670000
1%
1-
b1001 3
#1680000
0%
0-
#1690000
1%
1-
b0 3
0,
0@
0$
#1695000
b0 (
b0 #
0=
#1700000
0%
0-
#1710000
1%
1-
b1 3
#1720000
0%
0-
#1730000
1%
1-
b10 3
#1740000
0%
0-
#1750000
1%
1-
b11 3
#1760000
0%
0-
#1770000
1%
1-
b100 3
#1780000
0%
0-
#1790000
1%
1-
b101 3
#1800000
0%
0-
#1810000
1%
1-
b110 3
#1820000
0%
0-
#1830000
1%
1-
b111 3
#1840000
0%
0-
#1850000
1%
1-
b1000 3
#1860000
0%
0-
#1870000
1%
1-
b1001 3
#1880000
0%
0-
#1890000
1%
1-
b0 3
1,
1@
1$
#1900000
0%
0-
#1910000
1%
1-
b1 6
1?
18
b1 3
#1920000
0%
0-
#1930000
1%
1-
b10 6
b10 3
#1940000
0%
0-
#1950000
1%
1-
b11 6
b11 3
#1960000
0%
0-
#1970000
1%
1-
b100 6
b100 3
#1980000
0%
0-
#1990000
1%
1-
b101 6
b101 3
#2000000
0%
0-
#2010000
1%
1-
b110 6
b110 3
#2020000
0%
0-
#2030000
1%
1-
b111 6
b111 3
#2040000
0%
0-
#2050000
1%
1-
b1000 6
b1000 3
#2060000
0%
0-
#2070000
1%
1-
b1001 6
15
b1001 3
1A
0@
#2080000
0%
0-
#2090000
1%
1-
b0 6
08
17
b0 3
0,
0A
0$
#2100000
0%
0-
#2110000
1%
1-
b1 6
b1 3
#2120000
0%
0-
#2130000
1%
1-
b10 6
b10 3
#2140000
0%
0-
#2150000
1%
1-
b11 6
b11 3
#2160000
0%
0-
#2170000
1%
1-
b100 6
b100 3
#2180000
0%
0-
#2190000
1%
1-
b101 6
b101 3
#2200000
0%
0-
#2210000
1%
1-
b110 6
18
b110 3
#2220000
0%
0-
#2230000
1%
1-
b111 6
08
b111 3
#2240000
0%
0-
#2250000
1%
1-
b1000 6
18
b1000 3
#2260000
0%
0-
#2270000
1%
1-
b0 6
08
05
1>
b1001 3
#2280000
0%
0-
#2290000
1%
1-
b0 3
1,
1@
1$
#2300000
0%
0-
#2310000
1%
1-
b1 6
18
b1 3
#2320000
0%
0-
#2330000
1%
1-
b10 6
b10 3
#2340000
0%
0-
#2350000
1%
1-
b11 6
b11 3
#2360000
0%
0-
#2370000
1%
1-
b100 6
b100 3
#2380000
0%
0-
#2390000
1%
1-
b101 6
b101 3
#2400000
0%
0-
#2410000
1%
1-
b110 6
b110 3
#2420000
0%
0-
#2430000
1%
1-
b111 6
b111 3
#2440000
0%
0-
#2450000
1%
1-
b1000 6
b1000 3
#2460000
0%
0-
#2470000
1%
1-
b1001 6
15
b1001 3
1A
0@
#2480000
0%
0-
#2490000
1%
1-
b0 6
08
10
b0 3
0,
0A
0$
#2500000
0%
0-
#2510000
1%
1-
b1 6
b1 3
#2520000
0%
0-
#2530000
1%
1-
b10 6
b10 3
#2540000
0%
0-
#2550000
1%
1-
b11 6
b11 3
#2560000
0%
0-
#2570000
1%
1-
b100 6
b100 3
#2580000
0%
0-
#2590000
1%
1-
b101 6
b101 3
#2600000
0%
0-
#2610000
1%
1-
b110 6
18
b110 3
#2620000
0%
0-
#2630000
1%
1-
b111 6
08
b111 3
#2640000
0%
0-
#2650000
1%
1-
b1000 6
18
b1000 3
#2660000
0%
0-
#2670000
1%
1-
b0 6
08
05
b1001 3
#2680000
0%
0-
#2690000
1%
1-
b0 3
1,
1@
1$
#2700000
0%
0-
#2710000
1%
1-
b1 6
18
b1 3
#2720000
0%
0-
#2730000
1%
1-
b10 6
b10 3
#2740000
0%
0-
#2750000
1%
1-
b11 6
b11 3
#2760000
0%
0-
#2770000
1%
1-
b100 6
b100 3
#2780000
0%
0-
#2790000
1%
1-
b101 6
b101 3
#2800000
0%
0-
#2810000
1%
1-
b110 6
b110 3
#2820000
0%
0-
#2830000
1%
1-
b111 6
b111 3
#2840000
0%
0-
#2850000
1%
1-
b1000 6
b1000 3
#2860000
0%
0-
#2870000
1%
1-
b1001 6
15
b1001 3
1A
0@
#2880000
0%
0-
#2890000
1%
1-
b0 6
08
b0 3
0,
0A
0$
#2900000
0%
0-
#2910000
1%
1-
b1 6
b1 3
#2920000
0%
0-
#2930000
1%
1-
b10 6
b10 3
#2940000
0%
0-
#2950000
1%
1-
b11 6
b11 3
#2960000
0%
0-
#2970000
1%
1-
b100 6
b100 3
#2980000
0%
0-
#2990000
1%
1-
b101 6
b101 3
#3000000
0%
0-
#3010000
1%
1-
b110 6
18
b110 3
#3020000
0%
0-
#3030000
1%
1-
b111 6
08
b111 3
#3040000
0%
0-
#3050000
1%
1-
b1000 6
18
b1000 3
#3060000
0%
0-
#3070000
1%
1-
b0 6
08
05
b1001 3
#3080000
0%
0-
#3090000
1%
1-
b0 3
1,
1@
1$
#3100000
0%
0-
#3110000
1%
1-
b1 6
18
b1 3
#3120000
0%
0-
#3130000
1%
1-
b10 6
b10 3
#3140000
0%
0-
#3150000
1%
1-
b11 6
b11 3
#3160000
0%
0-
#3170000
1%
1-
b100 6
b100 3
#3180000
0%
0-
#3190000
1%
1-
b101 6
b101 3
#3200000
0%
0-
#3210000
1%
1-
b110 6
b110 3
#3220000
0%
0-
#3230000
1%
1-
b111 6
b111 3
#3240000
0%
0-
#3250000
1%
1-
b1000 6
b1000 3
#3260000
0%
0-
#3270000
1%
1-
b1001 6
15
b1001 3
1A
0@
#3280000
0%
0-
#3290000
1%
1-
b0 6
08
b0 3
0,
0A
0$
#3300000
0%
0-
#3310000
1%
1-
b1 6
b1 3
#3320000
0%
0-
#3330000
1%
1-
b10 6
b10 3
#3340000
0%
0-
#3350000
1%
1-
b11 6
b11 3
#3360000
0%
0-
#3370000
1%
1-
b100 6
b100 3
#3380000
0%
0-
#3390000
1%
1-
b101 6
b101 3
#3400000
0%
0-
#3410000
1%
1-
b110 6
18
b110 3
#3420000
0%
0-
#3430000
1%
1-
b111 6
08
b111 3
#3440000
0%
0-
#3450000
1%
1-
b1000 6
18
b1000 3
#3460000
0%
0-
#3470000
1%
1-
b0 6
08
05
b1001 3
#3480000
0%
0-
#3490000
1%
1-
b0 3
1,
1@
1$
#3500000
0%
0-
#3510000
1%
1-
b1 6
18
b1 3
#3520000
0%
0-
#3530000
1%
1-
b10 6
b10 3
#3540000
0%
0-
#3550000
1%
1-
b11 6
b11 3
#3560000
0%
0-
#3570000
1%
1-
b100 6
b100 3
#3580000
0%
0-
#3590000
1%
1-
b101 6
b101 3
#3600000
0%
0-
#3610000
1%
1-
b110 6
b110 3
#3620000
0%
0-
#3630000
1%
1-
b111 6
b111 3
#3640000
0%
0-
#3650000
1%
1-
b1000 6
b1000 3
#3660000
0%
0-
#3670000
1%
1-
b1001 6
15
b1001 3
1A
0@
#3680000
0%
0-
#3690000
1%
1-
b0 6
08
b0 3
0,
0A
0$
#3700000
0%
0-
#3710000
1%
1-
b1 6
b1 3
#3720000
0%
0-
#3730000
1%
1-
b10 6
b10 3
#3740000
0%
0-
#3750000
1%
1-
b11 6
b11 3
#3760000
0%
0-
#3770000
1%
1-
b100 6
b100 3
#3780000
0%
0-
#3790000
1%
1-
b101 6
b101 3
#3800000
0%
0-
#3810000
1%
1-
b110 6
18
b110 3
#3820000
0%
0-
#3830000
1%
1-
b111 6
08
b111 3
#3840000
0%
0-
#3850000
1%
1-
b1000 6
18
b1000 3
#3860000
0%
0-
#3870000
1%
1-
b0 6
08
05
b1001 3
#3880000
0%
0-
#3890000
1%
1-
b0 3
1,
1@
1$
#3900000
0%
0-
#3910000
1%
1-
b1 6
18
b1 3
#3920000
0%
0-
#3930000
0)
1%
1-
b10 6
b10 3
#3940000
0%
0-
#3950000
1%
1-
b11 6
b11 3
#3960000
0%
0-
#3970000
1%
1-
b100 6
b100 3
#3980000
0%
0-
#3990000
1%
1-
b101 6
b101 3
#4000000
0%
0-
#4010000
1%
1-
b110 6
b110 3
#4020000
0%
0-
#4030000
1%
1-
b111 6
b111 3
#4040000
0%
0-
#4050000
1%
1-
b1000 6
b1000 3
#4060000
0%
0-
#4070000
1%
1-
b1001 6
15
b1001 3
1A
0@
#4080000
0%
0-
#4090000
1%
1-
b0 6
08
b0 3
0,
0A
0$
bz #
z=
#4100000
0%
0-
#4110000
1%
1-
b1 6
b1 3
#4120000
0%
0-
#4130000
1%
1-
b10 6
b10 3
#4140000
0%
0-
#4150000
1%
1-
b11 6
b11 3
#4160000
0%
0-
#4170000
1%
1-
b100 6
b100 3
#4180000
0%
0-
#4190000
1%
1-
b101 6
b101 3
#4200000
0%
0-
#4210000
1%
1-
b110 6
18
b110 3
b0 #
0=
#4220000
0%
0-
#4230000
1%
1-
b111 6
08
b111 3
bz #
z=
#4240000
0%
0-
#4250000
1%
1-
b1000 6
18
b1000 3
b0 #
0=
#4260000
0%
0-
#4270000
1%
1-
b0 6
08
05
b1001 3
bz #
z=
#4280000
0%
0-
#4290000
1%
1-
b0 3
1,
x@
1$
#4300000
0%
0-
#4310000
1%
1-
0>
07
0?
b1 3
#4320000
0%
0-
#4330000
1%
1-
b10 3
#4340000
0%
0-
#4350000
1%
1-
b11 3
#4360000
0%
0-
#4370000
1%
1-
b100 3
#4380000
0%
0-
#4390000
1%
1-
b101 3
#4400000
0%
0-
#4410000
1%
1-
b110 3
#4420000
0%
0-
#4430000
1%
1-
b111 3
#4440000
0%
0-
#4450000
b1010101 B
1)
1%
1-
b0 #
0=
1@
b1000 3
#4460000
0%
0-
#4470000
1%
1-
b1 6
1?
18
b1001 3
#4480000
0%
0-
#4490000
1%
1-
b10 6
b0 3
0,
0@
0$
#4500000
0%
0-
#4510000
1%
1-
b1 3
#4520000
0%
0-
#4530000
1%
1-
b10 3
#4540000
0%
0-
#4550000
1%
1-
b11 3
#4560000
0%
0-
#4570000
1%
1-
b100 3
#4580000
0%
0-
#4590000
1%
1-
b101 3
#4600000
0%
0-
#4610000
1%
1-
b110 3
#4620000
0%
0-
#4630000
1%
1-
b111 3
#4640000
0%
0-
#4650000
1%
1-
b1000 3
#4660000
0%
0-
#4670000
1%
1-
b1001 3
#4680000
0%
0-
#4690000
1%
1-
b0 3
1,
1@
1$
#4700000
0%
0-
#4710000
1%
1-
b11 6
b1 3
#4720000
0%
0-
#4730000
1%
1-
b100 6
b10 3
#4740000
0%
0-
#4750000
1%
1-
b101 6
b11 3
#4760000
0%
0-
#4770000
1%
1-
b110 6
b100 3
#4780000
0%
0-
#4790000
1%
1-
b111 6
b101 3
#4800000
0%
0-
#4810000
1%
1-
b1000 6
b110 3
#4820000
0%
0-
#4830000
1%
1-
b1001 6
15
b111 3
1A
0@
#4840000
0%
0-
#4850000
1%
1-
b0 6
08
17
b1000 3
0A
1@
#4860000
0%
0-
#4870000
1%
1-
b1 6
18
b1001 3
#4880000
0%
0-
#4890000
1%
1-
b10 6
b0 3
0,
0@
0$
#4895000
bz (
#4900000
0%
0-
#4910000
1%
1-
b11 6
08
b1 3
bz #
z=
#4920000
0%
0-
#4930000
1%
1-
b100 6
b10 3
#4940000
0%
0-
#4950000
1%
1-
b101 6
b11 3
#4960000
0%
0-
#4970000
1%
1-
b110 6
18
b100 3
b0 #
0=
#4980000
0%
0-
#4990000
1%
1-
b111 6
08
b101 3
bz #
z=
#5000000
0%
0-
#5010000
1%
1-
b1000 6
18
b110 3
b0 #
0=
#5020000
0%
0-
#5030000
1%
1-
b0 6
08
05
1>
b111 3
bz #
z=
#5040000
0%
0-
#5050000
1%
1-
b1000 3
#5060000
0%
0-
#5070000
1%
1-
b1001 3
#5080000
0%
0-
#5090000
1%
1-
b0 3
1,
x@
1$
#5100000
0%
0-
#5110000
1%
1-
0>
07
0?
b1 3
#5120000
0%
0-
#5130000
1%
1-
b10 3
#5140000
0%
0-
#5150000
1%
1-
b11 3
#5160000
0%
0-
#5170000
1%
1-
b100 3
#5180000
0%
0-
#5190000
1%
1-
b101 3
#5200000
0%
0-
#5210000
1%
1-
b110 3
#5220000
0%
0-
#5230000
1%
1-
b111 3
#5240000
0%
0-
#5250000
1%
1-
b1000 3
#5260000
0%
0-
#5270000
1%
1-
b1001 3
#5280000
0%
0-
#5290000
1%
1-
b0 3
0,
0@
0$
#5295000
b0 (
b0 #
0=
#5300000
0%
0-
#5310000
1%
1-
b1 3
#5320000
0%
0-
#5330000
1%
1-
b10 3
#5340000
0%
0-
#5350000
1%
1-
b11 3
#5360000
0%
0-
#5370000
1%
1-
b100 3
#5380000
0%
0-
#5390000
1%
1-
b101 3
#5400000
0%
0-
#5410000
1%
1-
b110 3
#5420000
0%
0-
#5430000
1%
1-
b111 3
#5440000
0%
0-
#5450000
1%
1-
b1000 3
#5460000
0%
0-
#5470000
1%
1-
b1001 3
#5480000
0%
0-
#5490000
1%
1-
b0 3
1,
1@
1$
#5500000
0%
0-
#5510000
1%
1-
b1 6
1?
18
b1 3
#5520000
0%
0-
#5530000
1%
1-
b10 6
b10 3
#5540000
0%
0-
#5550000
1%
1-
b11 6
b11 3
#5560000
0%
0-
#5570000
1%
1-
b100 6
b100 3
#5580000
0%
0-
#5590000
1%
1-
b101 6
b101 3
#5600000
0%
0-
#5610000
1%
1-
b110 6
b110 3
#5620000
0%
0-
#5630000
1%
1-
b111 6
b111 3
#5640000
0%
0-
#5650000
1%
1-
b1000 6
b1000 3
#5660000
0%
0-
#5670000
1%
1-
b1001 6
15
b1001 3
1A
0@
#5680000
0%
0-
#5690000
1%
1-
b0 6
08
17
b0 3
0,
0A
0$
#5695000
bz (
bz #
z=
#5700000
0%
0-
#5710000
1%
1-
b1 6
b1 3
#5720000
0%
0-
#5730000
1%
1-
b10 6
b10 3
#5740000
0%
0-
#5750000
1%
1-
b11 6
b11 3
#5760000
0%
0-
#5770000
1%
1-
b100 6
b100 3
#5780000
0%
0-
#5790000
1%
1-
b101 6
b101 3
#5800000
0%
0-
#5810000
1%
1-
b110 6
18
b110 3
b0 #
0=
#5820000
0%
0-
#5830000
1%
1-
b111 6
08
b111 3
bz #
z=
#5840000
0%
0-
#5850000
1%
1-
b1000 6
18
b1000 3
b0 #
0=
#5860000
0%
0-
#5870000
1%
1-
b0 6
08
05
1>
b1001 3
bz #
z=
#5880000
0%
0-
#5890000
1%
1-
b0 3
1,
x@
1$
#5900000
0%
0-
#5910000
1%
1-
0>
07
0?
b1 3
#5920000
0%
0-
#5930000
1%
1-
b10 3
#5940000
0%
0-
#5950000
1%
1-
b11 3
#5960000
0%
0-
#5970000
1%
1-
b100 3
#5980000
0%
0-
#5990000
1%
1-
b101 3
#6000000
0%
0-
#6010000
1%
1-
b110 3
#6020000
0%
0-
#6030000
1%
1-
b111 3
#6040000
0%
0-
#6050000
1%
1-
b1000 3
#6060000
0%
0-
#6070000
1%
1-
b1001 3
#6080000
0%
0-
#6090000
1%
1-
b0 3
0,
0@
0$
#6095000
b0 (
b0 #
0=
#6100000
0%
0-
#6110000
1%
1-
b1 3
#6120000
0%
0-
#6130000
1%
1-
b10 3
#6140000
0%
0-
#6150000
1%
1-
b11 3
#6160000
0%
0-
#6170000
1%
1-
b100 3
#6180000
0%
0-
#6190000
1%
1-
b101 3
#6200000
0%
0-
#6210000
1%
1-
b110 3
#6220000
0%
0-
#6230000
1%
1-
b111 3
#6240000
0%
0-
#6250000
1%
1-
b1000 3
#6260000
0%
0-
#6270000
1%
1-
b1001 3
#6280000
0%
0-
#6290000
1%
1-
b0 3
1,
1@
1$
#6300000
0%
0-
#6310000
1%
1-
b1 6
1?
18
b1 3
#6320000
0%
0-
#6330000
1%
1-
b10 6
b10 3
#6340000
0%
0-
#6350000
1%
1-
b11 6
b11 3
#6360000
0%
0-
#6370000
1%
1-
b100 6
b100 3
#6380000
0%
0-
#6390000
1%
1-
b101 6
b101 3
#6400000
0%
0-
#6410000
1%
1-
b110 6
b110 3
#6420000
0%
0-
#6430000
1%
1-
b111 6
b111 3
#6440000
0%
0-
#6450000
1%
1-
b1000 6
b1000 3
#6460000
0%
0-
#6470000
1%
1-
b1001 6
15
b1001 3
1A
0@
#6480000
0%
0-
#6490000
1%
1-
b0 6
08
17
b0 3
0,
0A
0$
#6495000
bz (
bz #
z=
#6500000
0%
0-
#6510000
1%
1-
b1 6
b1 3
#6520000
0%
0-
#6530000
1%
1-
b10 6
b10 3
#6540000
0%
0-
#6550000
1%
1-
b11 6
b11 3
#6560000
0%
0-
#6570000
1%
1-
b100 6
b100 3
#6580000
0%
0-
#6590000
1%
1-
b101 6
b101 3
#6600000
0%
0-
#6610000
1%
1-
b110 6
18
b110 3
b0 #
0=
#6620000
0%
0-
#6630000
1%
1-
b111 6
08
b111 3
bz #
z=
#6640000
0%
0-
#6650000
1%
1-
b1000 6
18
b1000 3
b0 #
0=
#6660000
0%
0-
#6670000
1%
1-
b0 6
08
05
1>
b1001 3
bz #
z=
#6680000
0%
0-
#6690000
1%
1-
b0 3
1,
x@
1$
#6700000
0%
0-
#6710000
1%
1-
0>
07
0?
b1 3
#6720000
0%
0-
#6730000
1%
1-
b10 3
#6740000
0%
0-
#6750000
1%
1-
b11 3
#6760000
0%
0-
#6770000
1%
1-
b100 3
#6780000
0%
0-
#6790000
1%
1-
b101 3
#6800000
0%
0-
#6810000
1%
1-
b110 3
#6820000
0%
0-
#6830000
1%
1-
b111 3
#6840000
0%
0-
